{
    "default_header": "header_236213",
    "text-font": [
        {
            "google": "1",
            "font-family": "Inter",
            "font-weight": "400",
            "font-style": "",
            "font-subset": "",
            "font-size": "16",
            "tablet": {
                "font-size": ""
            },
            "mobile": {
                "font-size": ""
            },
            "color": "rgb(118,118,118)"
        }
    ],
    "primary-font": [
        {
            "google": "1",
            "font-family": "Roboto",
            "font-weight": "700",
            "font-style": "",
            "font-subset": "",
            "text-transform": "",
            "color": "#242424"
        }
    ],
    "post-titles-font": [
        {
            "google": "1",
            "font-family": "Roboto",
            "font-weight": "700",
            "font-style": "",
            "font-subset": "",
            "text-transform": "",
            "color": "#333333",
            "hover": {
                "color": "rgb(51 51 51 \/ 65%)"
            }
        }
    ],
    "widget-titles-font": [
        {
            "google": "1",
            "font-family": "Roboto",
            "font-weight": "700",
            "font-style": "",
            "font-subset": "",
            "text-transform": "uppercase",
            "font-size": "16",
            "tablet": {
                "font-size": ""
            },
            "mobile": {
                "font-size": ""
            },
            "color": "#333"
        }
    ],
    "navigation-font": [
        {
            "google": "1",
            "font-family": "Roboto",
            "font-weight": "500",
            "font-style": "",
            "font-subset": "",
            "text-transform": "uppercase",
            "font-size": "13",
            "tablet": {
                "font-size": ""
            },
            "mobile": {
                "font-size": ""
            }
        }
    ],
    "primary-color": {
        "idle": "rgb(26,61,151)"
    },
    "btns_shop_bg": {
        "idle": "rgb(26,61,151)"
    },
    "btns_shop_bg_hover": {
        "idle": "rgb(24,56,137)"
    },
    "footer_content_type": "html_block",
    "footer-bar-bg": {
        "color": "rgb(16,16,16)",
        "url": "",
        "id": "",
        "repeat": "",
        "size": "",
        "attachment": "",
        "position": ""
    },
    "footer-style": "light",
    "footer_html_block": "25114",
    "pages-background": {
        "color": "rgb(244,243,242)",
        "url": "",
        "id": "",
        "repeat": "",
        "size": "",
        "attachment": "",
        "position": ""
    },
    "secondary-font": [
        {
            "google": "1",
            "font-family": "Roboto",
            "font-weight": "500",
            "font-style": "",
            "font-subset": ""
        }
    ],
    "disable_copyrights": "0",
    "prefooter_content_type": "html_block",
    "prefooter_html_block": "",
    "form_border_width": "2",
    "sticky_toolbar": "0",
    "blog_design": "masonry",
    "blog_columns": "3",
    "blog_masonry": "0",
    "blog_archive_layout": "full-width"
}